modern_python_template/__init__.py
modern_python_template/console.py
modern_python_template/wikipedia.py
modern_python_template-1.2.0.dist-info/entry_points.txt
modern_python_template-1.2.0.dist-info/LICENSE
modern_python_template-1.2.0.dist-info/WHEEL
modern_python_template-1.2.0.dist-info/METADATA
modern_python_template-1.2.0.dist-info/RECORD
