Metadata-Version: 2.1
Name: modern-python-template
Version: 1.2.0
Summary: The Hypermordern Python Project
Home-page: https://github.com/VivekWisdom/modern-python-template
Author: Vivek Wisdom
Author-email: ervivekwisdom@gmail.com
Requires-Python: >=3.7,<4.0
Classifier: Programming Language :: Python :: 3
Classifier: Programming Language :: Python :: 3.7
Classifier: Programming Language :: Python :: 3.8
Classifier: Programming Language :: Python :: 3.9
Classifier: Programming Language :: Python :: 3.10
Requires-Dist: click (>=8.1.3,<9.0.0)
Requires-Dist: desert (>=2022.9.22,<2023.0.0)
Requires-Dist: importlib-metadata (>=4.12.0,<5.0.0); python_version < "3.8"
Requires-Dist: marshmallow (>=3.18.0,<4.0.0)
Requires-Dist: requests (>=2.28.1,<3.0.0)
Project-URL: Documentation, https://modern-python-template.readthedocs.io
Project-URL: Repository, https://github.com/VivekWisdom/modern-python-template
